print_ctf/__init__.py
print_ctf-1.0.4.dist-info/METADATA
print_ctf-1.0.4.dist-info/WHEEL
print_ctf-1.0.4.dist-info/entry_points.txt
print_ctf-1.0.4.dist-info/top_level.txt
print_ctf-1.0.4.dist-info/RECORD
